{
  "project_info": {
    "project_number": "69645261415",
    "firebase_url": "https://tutorbytee-default-rtdb.firebaseio.com",
    "project_id": "tutorbytee",
    "storage_bucket": "tutorbytee.appspot.com"
  },
  "client": [
    {
      "client_info": {
        "mobilesdk_app_id": "1:69645261415:android:e3d45e31724cbb688412c2",
        "android_client_info": {
          "package_name": "app.tutorbyte"
        }
      },
      "oauth_client": [],
      "api_key": [
        {
          "current_key": "AIzaSyCUfrNzMuMMFuh8kxG5b9oGliFycljtxgo"
        }
      ],
      "services": {
        "appinvite_service": {
          "other_platform_oauth_client": []
        }
      }
    },
    {
      "client_info": {
        "mobilesdk_app_id": "1:69645261415:android:451cb69608063a9f8412c2",
        "android_client_info": {
          "package_name": "com.ayush.tutoradmin"
        }
      },
      "oauth_client": [],
      "api_key": [
        {
          "current_key": "AIzaSyCUfrNzMuMMFuh8kxG5b9oGliFycljtxgo"
        }
      ],
      "services": {
        "appinvite_service": {
          "other_platform_oauth_client": []
        }
      }
    }
  ],
  "configuration_version": "1"
}